setup.py
espn_py/__init__.py
espn_py/espn.py
espn_py.egg-info/PKG-INFO
espn_py.egg-info/SOURCES.txt
espn_py.egg-info/dependency_links.txt
espn_py.egg-info/requires.txt
espn_py.egg-info/top_level.txt